pysoundtool/__init__.py
pysoundtool/augment.py
pysoundtool/builtin.py
pysoundtool/datasets.py
pysoundtool/dsp.py
pysoundtool/exceptions.py
pysoundtool/feats.py
pysoundtool/files.py
pysoundtool/filters.py
pysoundtool/utils.py
pysoundtool/models/__init__.py
pysoundtool/models/dataprep.py
pysoundtool/models/modelsetup.py
pysoundtool/models/plot.py
pysoundtool/models/template_models.py
pysoundtool_online/models/__init__.py
pysoundtool_online/models/dataprep.py
pysoundtool_online/models/modelsetup.py
pysoundtool_online/models/plot.py
pysoundtool_online/models/template_models.py
pysoundtool-0.1.0a1.dist-info/LICENSE.md
pysoundtool-0.1.0a1.dist-info/METADATA
pysoundtool-0.1.0a1.dist-info/WHEEL
pysoundtool-0.1.0a1.dist-info/top_level.txt
pysoundtool-0.1.0a1.dist-info/RECORD
