Metadata-Version: 2.1
Name: pysoundtool
Version: 0.1.0a1
Summary: A research-based framework for exploring sound as well as machine learning in the context of sound.
Home-page: https://github.com/a-n-rose/Python-Sound-Tool
Author: Aislyn Rose
Author-email: rose.aislyn.noelle@gmail.com
License: AGPL-3.0
Platform: UNKNOWN
Classifier: License :: OSI Approved :: GNU Affero General Public License v3
Classifier: Programming Language :: Python :: 3
Classifier: Programming Language :: Python :: 3.6
Requires-Python: ==3.6.9
Requires-Dist: numpy (==1.17.1)
Requires-Dist: python-speech-features (==0.6)
Requires-Dist: scipy (==1.3.1)
Requires-Dist: scikit-learn (==0.21.3)
Requires-Dist: keras (==2.3.0)
Requires-Dist: tensorflow (==1.15.2)
Requires-Dist: librosa (==0.7.2)
Requires-Dist: matplotlib (==3.1.1)
Requires-Dist: soundfile (==0.10.3.post1)
Requires-Dist: numba (==0.48)
